langchain_pymupdf_layout/__init__.py
langchain_pymupdf_layout/pymupdf_layout_loader.py
langchain_pymupdf_layout/pymupdf_layout_parser.py
langchain_pymupdf_layout-0.1.0.dist-info/licenses/LICENSE
langchain_pymupdf_layout-0.1.0.dist-info/METADATA
langchain_pymupdf_layout-0.1.0.dist-info/WHEEL
langchain_pymupdf_layout-0.1.0.dist-info/top_level.txt
langchain_pymupdf_layout-0.1.0.dist-info/RECORD
