Metadata-Version: 2.4
Name: langchain-pymupdf-layout
Version: 0.1.0
Summary: An integration package connecting PyMuPDF Layout to LangChain. Load PDF content to Markdown using AI-based, CPU only, layout analysis.
Author-email: Jamie Lemon <jamie.lemon@artifex.com>
License: # PolyForm Noncommercial License 1.0.0
Requires-Python: >=3.7
License-File: LICENSE
Requires-Dist: langchain-core<2.0.0,>=1.0.0
Requires-Dist: pymupdf>=0.26.6
Requires-Dist: pymupdf-layout>=0.26.6
Requires-Dist: pymupdf4llm>=0.2.0
Dynamic: license-file
